cogs/__init__.py
cogs/__main__.py
cogs/add.py
cogs/apply.py
cogs/clear.py
cogs/cli.py
cogs/connect.py
cogs/delete.py
cogs/diff.py
cogs/exceptions.py
cogs/fetch.py
cogs/helpers.py
cogs/ignore.py
cogs/init.py
cogs/ls.py
cogs/merge.py
cogs/mv.py
cogs/push.py
cogs/rm.py
cogs/share.py
cogs/status.py
ontodev_cogs-0.3.3.dist-info/LICENSE
ontodev_cogs-0.3.3.dist-info/METADATA
ontodev_cogs-0.3.3.dist-info/WHEEL
ontodev_cogs-0.3.3.dist-info/entry_points.txt
ontodev_cogs-0.3.3.dist-info/top_level.txt
ontodev_cogs-0.3.3.dist-info/RECORD
