Metadata-Version: 2.1
Name: ontodev-cogs
Version: 0.3.3
Summary: COGS Operates Google Sheets
Home-page: https://github.com/ontodev/cogs
Author: Rebecca C Jackson
Author-email: rbca.jackson@gmail.com
License: UNKNOWN
Platform: UNKNOWN
Classifier: Programming Language :: Python :: 3
Classifier: Environment :: Console
Classifier: Operating System :: OS Independent
Classifier: License :: OSI Approved :: BSD License
Requires-Python: >=3.6, <4
Requires-Dist: daff
Requires-Dist: google
Requires-Dist: google-api-python-client
Requires-Dist: gspread
Requires-Dist: gspread-formatting
Requires-Dist: requests
Requires-Dist: tabulate
Requires-Dist: termcolor
